starlette_bridge/__init__.py
starlette_bridge/bridge.py
starlette_bridge/context_managers.py
starlette_bridge/py.typed
starlette_bridge/routing.py
starlette_bridge-0.3.0.dist-info/METADATA
starlette_bridge-0.3.0.dist-info/WHEEL
starlette_bridge-0.3.0.dist-info/licenses/LICENSE
starlette_bridge-0.3.0.dist-info/RECORD
